{
    "elasticsearch": {
        "arch": "amd64",
        "digest": "8928590bec3c6efe7f0e4f4694574d471a8bd3658208182916ed2539bb9090f1",
        "distro": "debian-11",
        "type": "NAMI",
        "version": "8.6.2-1"
    },
    "gosu": {
        "arch": "amd64",
        "digest": "f6056076afb745fd7d9d87d20f71e7248d63330352cf5ae0be2130b7f44a8cfa",
        "distro": "debian-11",
        "type": "NAMI",
        "version": "1.16.0-2"
    },
    "java": {
        "arch": "amd64",
        "digest": "09eb316f02e065beb59e8c3cc8f2f908879faf7f4902cd1cc4b9fcd25bd528ca",
        "distro": "debian-11",
        "type": "NAMI",
        "version": "17.0.6-10-2"
    },
    "yq": {
        "arch": "amd64",
        "digest": "498dd1e7ac81a0e41ac2761d6708e425bab6cbbf37c93e47ce8df12000e8a4d3",
        "distro": "debian-11",
        "type": "NAMI",
        "version": "4.31.2-0"
    }
}