{
    "couchdb": {
        "arch": "amd64",
        "digest": "48ec0edc501d9a4f95d6875217e57cc293c1d4db344a96c391616daebdebf53e",
        "distro": "debian-11",
        "type": "NAMI",
        "version": "3.3.1-5"
    },
    "erlang": {
        "arch": "amd64",
        "digest": "673f5a1b6fa64f1ed8646d1e29324941cb0c36de7d650604d34082cbcdcf216f",
        "distro": "debian-11",
        "type": "NAMI",
        "version": "25.3.0-0"
    },
    "gosu": {
        "arch": "amd64",
        "digest": "f6056076afb745fd7d9d87d20f71e7248d63330352cf5ae0be2130b7f44a8cfa",
        "distro": "debian-11",
        "type": "NAMI",
        "version": "1.16.0-2"
    },
    "ini-file": {
        "arch": "amd64",
        "digest": "75d5f74f62ca3a476e5ffc01715b197ba18c3b45a85b18fb61cc68e998616119",
        "distro": "debian-11",
        "type": "NAMI",
        "version": "1.4.5-1"
    },
    "wait-for-port": {
        "arch": "amd64",
        "digest": "be7c393d598ddf16d1c3c008a67b87879e48aca62071a208583390f2b41e6744",
        "distro": "debian-11",
        "type": "NAMI",
        "version": "1.0.6-1"
    }
}