{
    "ghost": {
        "arch": "amd64",
        "digest": "b09b689e2064446e602f4c5985d51e6118c3d6ca2811319aaa128a2062d10747",
        "distro": "debian-11",
        "type": "NAMI",
        "version": "5.16.0-0"
    },
    "gosu": {
        "arch": "amd64",
        "digest": "e36c3d90f4fbfbe989f40947fa7c8ab817f12fcf97d3aef893c753a20ce976ab",
        "distro": "debian-11",
        "type": "NAMI",
        "version": "1.14.0-154"
    },
    "mysql-client": {
        "arch": "amd64",
        "digest": "8a1d2ee97e1e6b337254b886f99392ea181cc1708965212e776b205dd61731a2",
        "distro": "debian-11",
        "type": "NAMI",
        "version": "10.6.10-0"
    },
    "node": {
        "arch": "amd64",
        "digest": "49946e0443d8f479f296c79589fea205126b6f6faa6b4474e5dd713b36d8167c",
        "distro": "debian-11",
        "type": "NAMI",
        "version": "14.20.0-3"
    },
    "python": {
        "arch": "amd64",
        "digest": "b81946d0fc75ce5dd9518d601920b6da4b24fbd87ca81a4cbd59404dd893764f",
        "distro": "debian-11",
        "type": "NAMI",
        "version": "3.8.14-1"
    }
}