{
    "ghost": {
        "arch": "amd64",
        "distro": "debian-11",
        "type": "NAMI",
        "version": "5.79.0-0"
    },
    "mysql-client": {
        "arch": "amd64",
        "distro": "debian-11",
        "type": "NAMI",
        "version": "10.11.6-2"
    },
    "node": {
        "arch": "amd64",
        "distro": "debian-11",
        "type": "NAMI",
        "version": "18.19.0-1"
    },
    "python": {
        "arch": "amd64",
        "distro": "debian-11",
        "type": "NAMI",
        "version": "3.11.7-3"
    }
}