{
    "consul": {
        "arch": "amd64",
        "digest": "a40892a80c8339545b2c92a5b8e5fce6c9ffa1ad7de17eb0662f7297ce9599bd",
        "distro": "debian-11",
        "type": "NAMI",
        "version": "1.14.3-0"
    },
    "gosu": {
        "arch": "amd64",
        "digest": "7969f4cc8ad0a260f891cccf5694686a513f4706b48771d605645be1f3f072e2",
        "distro": "debian-11",
        "type": "NAMI",
        "version": "1.14.0-156"
    },
    "render-template": {
        "arch": "amd64",
        "digest": "045804695ee2c857d91f28ba623f8c5f6898f5ae9016ee78504d3af76411c261",
        "distro": "debian-11",
        "type": "NAMI",
        "version": "1.0.4-1"
    }
}