{
    "gosu": {
        "arch": "amd64",
        "digest": "7969f4cc8ad0a260f891cccf5694686a513f4706b48771d605645be1f3f072e2",
        "distro": "debian-11",
        "type": "NAMI",
        "version": "1.14.0-156"
    },
    "redis": {
        "arch": "amd64",
        "digest": "985baa5af26a4987c33b2fa5e1287b1be455860f294713c5404a418c3e67867e",
        "distro": "debian-11",
        "type": "NAMI",
        "version": "7.0.6-0"
    },
    "wait-for-port": {
        "arch": "amd64",
        "digest": "6b1bd6f534ef27b696922dcbdc0e377ac1a7db1e2bc1ff688ae0fa80bbfcb618",
        "distro": "debian-11",
        "type": "NAMI",
        "version": "1.0.5-1"
    }
}