{
    "airflow-scheduler": {
        "arch": "amd64",
        "digest": "c922a5626583a76321e2062bd7ab934356dd45c6e59770f283fee1a8cc9e0309",
        "distro": "debian-11",
        "type": "NAMI",
        "version": "2.5.0-1"
    },
    "gosu": {
        "arch": "amd64",
        "digest": "c42abbc5d57ba4c33c89e4daf46c33b0173565fbf533ef7a60281cf3283f611f",
        "distro": "debian-11",
        "type": "NAMI",
        "version": "1.16.0-0"
    },
    "ini-file": {
        "arch": "amd64",
        "digest": "9b5793ab94c63d6384a29c88c06b3e33cf718112edc8358ac54ada72072c3f3e",
        "distro": "debian-11",
        "type": "NAMI",
        "version": "1.4.4-1"
    },
    "postgresql-client": {
        "arch": "amd64",
        "digest": "b52b264c1ed3c900d650d320317d66287e15a734ab6e94de10270c939cc6ab75",
        "distro": "debian-11",
        "type": "NAMI",
        "version": "15.1.0-0"
    },
    "python": {
        "arch": "amd64",
        "digest": "9a983efb0d4322a940f479c95983a78dbb02e8f3cc6e23b8b51b388add024b20",
        "distro": "debian-11",
        "type": "NAMI",
        "version": "3.9.16-0"
    },
    "wait-for-port": {
        "arch": "amd64",
        "digest": "6b1bd6f534ef27b696922dcbdc0e377ac1a7db1e2bc1ff688ae0fa80bbfcb618",
        "distro": "debian-11",
        "type": "NAMI",
        "version": "1.0.5-1"
    }
}