{
    "node": {
        "arch": "amd64",
        "distro": "debian-11",
        "type": "NAMI",
        "version": "18.17.0-2"
    },
    "odoo": {
        "arch": "amd64",
        "distro": "debian-11",
        "type": "NAMI",
        "version": "16.0.20230715-1"
    },
    "postgresql-client": {
        "arch": "amd64",
        "distro": "debian-11",
        "type": "NAMI",
        "version": "15.3.0-2"
    },
    "python": {
        "arch": "amd64",
        "distro": "debian-11",
        "type": "NAMI",
        "version": "3.10.12-4"
    },
    "render-template": {
        "arch": "amd64",
        "distro": "debian-11",
        "type": "NAMI",
        "version": "1.0.5-10"
    }
}