{
  "firstName": "{{$global.env.PRESTASHOP_FIRST_NAME}}",
  "lastName": "{{$global.env.PRESTASHOP_LAST_NAME}}",
  "password": "{{$global.env.PRESTASHOP_PASSWORD}}",
  "email": "{{$global.env.PRESTASHOP_EMAIL}}",
  "host": "{{$global.env.PRESTASHOP_HOST}}",
  "databaseAdminUser": "{{$global.env.MARIADB_USER}}",
  "databaseAdminPassword": "{{$global.env.MARIADB_PASSWORD}}",
  "databaseServerHost": "{{$global.env.MARIADB_HOST}}",
  "databaseServerPort": "{{$global.env.MARIADB_PORT}}",
  "smtpHost": "{{$global.env.SMTP_HOST}}",
  "smtpPort": "{{$global.env.SMTP_PORT}}",
  "smtpUser": "{{$global.env.SMTP_USER}}",
  "smtpPassword": "{{$global.env.SMTP_PASSWORD}}",
  "smtpProtocol": "{{$global.env.SMTP_PROTOCOL}}"
}