{
    "elasticsearch": {
        "arch": "amd64",
        "digest": "e0d75cb2521b74f9b6a5486273e4b899a71c8f6bbc543b382c984e622b4299f4",
        "distro": "debian-10",
        "type": "NAMI",
        "version": "7.16.2-1"
    },
    "gosu": {
        "arch": "amd64",
        "digest": "16f1a317859b06ae82e816b30f98f28b4707d18fe6cc3881bff535192a7715dc",
        "distro": "debian-10",
        "type": "NAMI",
        "version": "1.14.0-1"
    },
    "java": {
        "arch": "amd64",
        "digest": "cf2e298428d67fb30c376ee6638c055afe54cc1f282bab314abc53a34c37be44",
        "distro": "debian-10",
        "type": "NAMI",
        "version": "11.0.13-1"
    },
    "yq": {
        "arch": "amd64",
        "digest": "1c135708aaa8cb69936471de63563de08e97b7d0bfb4126d41b54a149557c5c0",
        "distro": "debian-10",
        "type": "NAMI",
        "version": "4.16.2-2"
    }
}