{
    "apache": {
        "arch": "amd64",
        "digest": "0296bc7dd5f621eba6f948433a6c7fc04a45876f42f6395cea5888b707f1ad11",
        "distro": "debian-10",
        "type": "NAMI",
        "version": "2.4.48-1"
    },
    "drupal": {
        "arch": "amd64",
        "digest": "d70ff85c68756d3eb8c0c0dc7c6b932f9e188dffa2ab3e011ca2da50f1bdf671",
        "distro": "debian-10",
        "type": "NAMI",
        "version": "8.9.18-0"
    },
    "gosu": {
        "arch": "amd64",
        "digest": "3e6fc37ca073b10a73a804d39c2f0c028947a1a596382a4f8ebe43dfbaa3a25e",
        "distro": "debian-10",
        "type": "NAMI",
        "version": "1.14.0-0"
    },
    "libphp": {
        "arch": "amd64",
        "digest": "02c944de0d39725adebf8a16960ceff5448f9d75d8ea8dc8228692baadee7659",
        "distro": "debian-10",
        "type": "NAMI",
        "version": "7.4.22-1"
    },
    "mysql-client": {
        "arch": "amd64",
        "digest": "92b99c64a3ffe10fd94ef9ecd94d2dd65a172404c726093eb50b3b293523559d",
        "distro": "debian-10",
        "type": "NAMI",
        "version": "10.3.31-0"
    },
    "php": {
        "arch": "amd64",
        "digest": "3ef2eb24c358a84f03bf1eee1747a1379bac7ab2c54601abae4423a72ed6f843",
        "distro": "debian-10",
        "type": "NAMI",
        "version": "7.4.22-1"
    },
    "render-template": {
        "arch": "amd64",
        "digest": "8179ad1371c9a7d897fe3b1bf53bbe763f94edafef19acad2498dd48b3674efe",
        "distro": "debian-10",
        "type": "NAMI",
        "version": "1.0.0-3"
    }
}