{
    "etcd": {
        "arch": "amd64",
        "digest": "34c0b9a3d60063b82d702a5ab227f2633c9d13ff814d872fd3c54733b4474594",
        "distro": "debian-11",
        "type": "NAMI",
        "version": "3.4.24-0"
    },
    "gosu": {
        "arch": "amd64",
        "digest": "f6056076afb745fd7d9d87d20f71e7248d63330352cf5ae0be2130b7f44a8cfa",
        "distro": "debian-11",
        "type": "NAMI",
        "version": "1.16.0-2"
    },
    "yq": {
        "arch": "amd64",
        "digest": "2fcd60b9977991e83f7066cf6da2c319b21483cdc67597625af37fa753534faf",
        "distro": "debian-11",
        "type": "NAMI",
        "version": "4.30.8-2"
    }
}