{
    "java": {
        "arch": "amd64",
        "digest": "68b909cfb5c98625e7d0db5c6eb82a34eca9b8940ada38b7eaa0c238bb510b57",
        "distro": "debian-10",
        "type": "NAMI",
        "version": "11.0.10-0"
    },
    "jruby": {
        "arch": "amd64",
        "digest": "10f738f85da51392d9e0765e69fc733d3d5061b1124e68b0d6481b9f1fb37530",
        "distro": "debian-10",
        "type": "NAMI",
        "version": "9.2.14-0-3"
    },
    "node": {
        "arch": "amd64",
        "digest": "ed45a2b5de321503ee749e67ab3118a7d28ce1740b709206fdff7834d59bbe24",
        "distro": "debian-10",
        "type": "NAMI",
        "version": "14.15.5-1"
    }
}