{
    "gosu": {
        "arch": "amd64",
        "digest": "4d858ac600c38af8de454c27b7f65c0074ec3069880cb16d259a6e40a46bbc50",
        "distro": "debian-10",
        "type": "NAMI",
        "version": "1.12.0-2"
    },
    "mongodb": {
        "arch": "amd64",
        "digest": "85a13d46d1d4a8e55fe5f696928588b2443a69828abdc881587340b53e544bbd",
        "distro": "debian-10",
        "type": "NAMI",
        "version": "4.4.1-1"
    },
    "render-template": {
        "arch": "amd64",
        "digest": "f1bee333423f6627d795ea9e0b6a89c18d2e5c2e2d015bb4620f040f1d520cf6",
        "distro": "debian-10",
        "type": "NAMI",
        "version": "1.0.0-2"
    },
    "wait-for-port": {
        "arch": "amd64",
        "digest": "7521d9a4f9e4e182bf32977e234026caa7b03759799868335bccb1edd8f8fd12",
        "distro": "debian-10",
        "type": "NAMI",
        "version": "1.0.0-3"
    },
    "yq": {
        "arch": "amd64",
        "digest": "a8889ed389089d58955bd5b30d562d612ea540d5bbe5338bc4e68a9e1665c38f",
        "distro": "debian-10",
        "type": "NAMI",
        "version": "3.4.0-1"
    }
}