{
    "gosu": {
        "arch": "amd64",
        "digest": "d6280b6f647a62bf6edc74dc8e526bfff63ddd8067dcb8540843f47203d9ccf1",
        "distro": "debian-10",
        "type": "NAMI",
        "version": "1.14.0-7"
    },
    "python": {
        "arch": "amd64",
        "digest": "a328c8fb3db9e60d3aa19eb7ca31de5da372affcb3d7c0d73610b4a19b634f94",
        "distro": "debian-10",
        "type": "NAMI",
        "version": "3.8.13-3"
    },
    "pytorch-intel": {
        "arch": "amd64",
        "digest": "bf270e2ba67e176fe8fe6c21120c722f326e11c3ce2e62cd5528b36fcf9ae83d",
        "distro": "debian-10",
        "type": "NAMI",
        "version": "1.10.2-0"
    }
}