{
    "gosu": {
        "arch": "amd64",
        "digest": "0c751c7e2ec0bc900a19dbec0306d6294fe744ddfb0fa64197ba1a36040092f0",
        "distro": "debian-11",
        "type": "NAMI",
        "version": "1.14.0-152"
    },
    "java": {
        "arch": "amd64",
        "digest": "6d176a8b3c894c608106fee2cf10aaf3771015defb0b7e08fe60ce6c9c1cd342",
        "distro": "debian-11",
        "type": "NAMI",
        "version": "11.0.15-1-1"
    },
    "render-template": {
        "arch": "amd64",
        "digest": "9690a34674f152e55c71a55275265314ed1bb29e0be8a75d7880488509f70deb",
        "distro": "debian-11",
        "type": "NAMI",
        "version": "1.0.3-151"
    },
    "tomcat": {
        "arch": "amd64",
        "digest": "cc5ec8f674abfb18c745f3656356aa83344bc0d9ff24024bffd3f85ef485514c",
        "distro": "debian-11",
        "type": "NAMI",
        "version": "9.0.65-0"
    }
}