{
    "etcd": {
        "arch": "amd64",
        "digest": "797710c466d87cb86c82b1b03e90bc7747bac8d4f3ec370796cbf16ce050627a",
        "distro": "debian-11",
        "type": "NAMI",
        "version": "3.5.7-2"
    },
    "gosu": {
        "arch": "amd64",
        "digest": "f6056076afb745fd7d9d87d20f71e7248d63330352cf5ae0be2130b7f44a8cfa",
        "distro": "debian-11",
        "type": "NAMI",
        "version": "1.16.0-2"
    },
    "yq": {
        "arch": "amd64",
        "digest": "83bb15cc1ad5d561294aa058542a9160685b976c866a303208c10e7c08634a8f",
        "distro": "debian-11",
        "type": "NAMI",
        "version": "4.31.1-0"
    }
}