{
    "gosu": {
        "arch": "amd64",
        "digest": "fd7257c2736164d02832dbf72e2c1ed9d875bf3e32f0988520796bc503330129",
        "distro": "debian-10",
        "type": "NAMI",
        "version": "1.13.0-0"
    },
    "influxdb": {
        "arch": "amd64",
        "digest": "5ee64bc6a2344c12bbfa857f469acb6e7c6a454c35b5fda918daf672284e842a",
        "distro": "debian-10",
        "type": "NAMI",
        "version": "2.0.7-0"
    },
    "wait-for-port": {
        "arch": "amd64",
        "digest": "7521d9a4f9e4e182bf32977e234026caa7b03759799868335bccb1edd8f8fd12",
        "distro": "debian-10",
        "type": "NAMI",
        "version": "1.0.0-3"
    }
}