{
    "erlang": {
        "arch": "amd64",
        "digest": "197edf49df1a59a155921687cc9eb3134b61bf33973b7d3bff20f71be4cee5d4",
        "distro": "debian-11",
        "type": "NAMI",
        "version": "24.3.4-7-1"
    },
    "gosu": {
        "arch": "amd64",
        "digest": "9ab9654690d90d3c49ff66fb1eb286487e318adc899d036bc45922f6b176865b",
        "distro": "debian-11",
        "type": "NAMI",
        "version": "1.16.0-1"
    },
    "rabbitmq": {
        "arch": "amd64",
        "digest": "5c2ce7b124e9860287cdfb9b20718b22dc23c98009d58613ea333f6f671c80fe",
        "distro": "debian-11",
        "type": "NAMI",
        "version": "3.9.27-2"
    }
}