{
    "gosu": {
        "arch": "amd64",
        "digest": "7969f4cc8ad0a260f891cccf5694686a513f4706b48771d605645be1f3f072e2",
        "distro": "debian-11",
        "type": "NAMI",
        "version": "1.14.0-156"
    },
    "mongodb": {
        "arch": "amd64",
        "digest": "96d14df7585039be0e606b27fbba1826bb24d16d800998ab7f2007f4d06818ca",
        "distro": "debian-11",
        "type": "NAMI",
        "version": "5.0.14-0"
    },
    "mongodb-shell": {
        "arch": "amd64",
        "digest": "62f93a1f29257014cb2ce2183e7ee9fcf926321f5fb592a7e1033107230e1baf",
        "distro": "debian-11",
        "type": "NAMI",
        "version": "1.6.0-1"
    },
    "render-template": {
        "arch": "amd64",
        "digest": "045804695ee2c857d91f28ba623f8c5f6898f5ae9016ee78504d3af76411c261",
        "distro": "debian-11",
        "type": "NAMI",
        "version": "1.0.4-1"
    },
    "wait-for-port": {
        "arch": "amd64",
        "digest": "6b1bd6f534ef27b696922dcbdc0e377ac1a7db1e2bc1ff688ae0fa80bbfcb618",
        "distro": "debian-11",
        "type": "NAMI",
        "version": "1.0.5-1"
    },
    "yq": {
        "arch": "amd64",
        "digest": "4262069ceb64e0e33d8f5af5fa4b7d06760a2b96ab2388418823a3c4346e9258",
        "distro": "debian-11",
        "type": "NAMI",
        "version": "4.30.5-0"
    }
}