{
    "gosu": {
        "arch": "amd64",
        "digest": "276ab5a0be4b05e136ec468d62c8f9cc4f40d9664c55f01f16a9f1209ba16980",
        "distro": "debian-10",
        "type": "NAMI",
        "version": "1.14.0-3"
    },
    "java": {
        "arch": "amd64",
        "digest": "02f54928e3049660ccebfc9a6d348bfaf27c9eb5abf70ebad45962b88f38473d",
        "distro": "debian-10",
        "type": "NAMI",
        "version": "1.8.322-4"
    },
    "spring-cloud-dataflow": {
        "arch": "amd64",
        "digest": "37ce7a1e509179a79802f70a9d075c282f7bce1f023edd6670c410da0b647ead",
        "distro": "debian-10",
        "type": "NAMI",
        "version": "2.9.2-3"
    },
    "yq": {
        "arch": "amd64",
        "digest": "fc3246374edb10a2d65df05c27187396ade8f91cb86e38b071704dcadde13802",
        "distro": "debian-10",
        "type": "NAMI",
        "version": "4.19.1-0"
    }
}