{
    "gosu": {
        "arch": "amd64",
        "digest": "d6280b6f647a62bf6edc74dc8e526bfff63ddd8067dcb8540843f47203d9ccf1",
        "distro": "debian-10",
        "type": "NAMI",
        "version": "1.14.0-7"
    },
    "laravel": {
        "arch": "amd64",
        "digest": "f5a5d336ed99c8fb81262538490b2969e9aefe70060603f7c0dafc61cfa22a3c",
        "distro": "debian-10",
        "type": "NAMI",
        "version": "9.1.3-0"
    },
    "node": {
        "arch": "amd64",
        "digest": "806082b15c0eb60e4baca497519b4c0cc9cd636d7a944e9943ebc1b9632fabdc",
        "distro": "debian-10",
        "type": "NAMI",
        "version": "14.19.1-0"
    },
    "php": {
        "arch": "amd64",
        "digest": "540ca94a39d500ed9e6bba61cda5ff89929d7959b80daf5b3e1e44327bc9f336",
        "distro": "debian-10",
        "type": "NAMI",
        "version": "8.1.4-3"
    },
    "python": {
        "arch": "amd64",
        "digest": "704fe6b545280ae027303b4ec875b495ee6da2256b3d8f877467077b0f031a60",
        "distro": "debian-10",
        "type": "NAMI",
        "version": "3.8.13-2"
    },
    "wait-for-port": {
        "arch": "amd64",
        "digest": "35c818ba3f4b5aae905959bc7d3a5e81fc63786e3c662b604612c0aa7fcda8fd",
        "distro": "debian-10",
        "type": "NAMI",
        "version": "1.0.1-10"
    }
}