{
    "git": {
        "arch": "amd64",
        "digest": "bda714065995df169ab17f11b3a638a106aec83b00bcbfb325b36b51f29d1704",
        "distro": "debian-10",
        "type": "NAMI",
        "version": "2.28.0-0"
    },
    "gosu": {
        "arch": "amd64",
        "digest": "51cfb1b7fd7b05b8abd1df0278c698103a9b1a4964bdacd87ca1d5c01631d59c",
        "distro": "debian-10",
        "type": "NAMI",
        "version": "1.12.0-1"
    },
    "jasperreports": {
        "arch": "amd64",
        "digest": "39ad907a4a6e87a0142a9a957f3dea58afaf72e3f366c3ef89ac83f1de55da56",
        "distro": "debian-10",
        "type": "NAMI",
        "version": "7.5.0-0"
    },
    "java": {
        "arch": "amd64",
        "digest": "7ccaf9b2abc4069482fea3d612e53c3b2a369e44c69e246aa8e8d7bddb496372",
        "distro": "debian-10",
        "type": "NAMI",
        "version": "1.8.262-0"
    },
    "mysql-client": {
        "arch": "amd64",
        "digest": "efab843077267af6a8cde53440a1fef0acf8cb67ab1dcd0b6da2e9cbe050c7e1",
        "distro": "debian-10",
        "type": "NAMI",
        "version": "10.3.23-1"
    },
    "tini": {
        "arch": "amd64",
        "digest": "9a8ae20be31a518f042fcec359f2cf35bfdb4e2a56f2fa8ff9ef2ecaf45da80c",
        "distro": "debian-10",
        "type": "NAMI",
        "version": "0.19.0-0"
    },
    "tomcat": {
        "arch": "amd64",
        "digest": "91e816aac9ad4bbace9fae1b6f472fcdaf9e0b1fad9be3a21cf8173b50cedc8b",
        "distro": "debian-10",
        "type": "NAMI",
        "version": "9.0.37-2"
    }
}