{
    "gosu": {
        "arch": "amd64",
        "digest": "9ab9654690d90d3c49ff66fb1eb286487e318adc899d036bc45922f6b176865b",
        "distro": "debian-11",
        "type": "NAMI",
        "version": "1.16.0-1"
    },
    "node": {
        "arch": "amd64",
        "digest": "c584387a554d2de02d1be7f8bf6ee003f2648f4fbbd8cee66dc04e9cb0ae1d45",
        "distro": "debian-11",
        "type": "NAMI",
        "version": "16.19.0-1"
    },
    "parse-dashboard": {
        "arch": "amd64",
        "digest": "c477748f5a159211f340280ecb7e7488f2c965161eb4b1fdb0b6801def9fc432",
        "distro": "debian-11",
        "type": "NAMI",
        "version": "5.0.0-1"
    },
    "python": {
        "arch": "amd64",
        "digest": "5baedbb7b4cd8e626842e71320bfe8cc4866b7238c5e8479c5426b9123c7dba0",
        "distro": "debian-11",
        "type": "NAMI",
        "version": "3.8.16-1"
    }
}