{
    "gosu": {
        "arch": "amd64",
        "digest": "7419bc5e2be68eb14c92e321acc843413481cda73323fb8c0d1dda8b1e5aa9d5",
        "distro": "debian-10",
        "type": "NAMI",
        "version": "1.14.0-2"
    },
    "kibana": {
        "arch": "amd64",
        "digest": "e5bd5df040064f6f72804e5ea0b53ff2ce42056832fbfa7b1f41c3747c7bd045",
        "distro": "debian-10",
        "type": "NAMI",
        "version": "7.10.2-6"
    },
    "yq": {
        "arch": "amd64",
        "digest": "e44965c2d2878443baa6c21214be5ce416a0ba34aaa3b23127ceb3aaefc72b4a",
        "distro": "debian-10",
        "type": "NAMI",
        "version": "4.17.2-0"
    }
}