{
    "gosu": {
        "arch": "amd64",
        "digest": "ec62006ece7e0b49c65926e458ba2b71d6d251552118b1378840b1803dbb3d53",
        "distro": "debian-10",
        "type": "NAMI",
        "version": "1.14.0-4"
    },
    "node": {
        "arch": "amd64",
        "digest": "400fb188f20ebb22fe9a99f6ef46598902884b9fbd87da481455cbc60273497d",
        "distro": "debian-10",
        "type": "NAMI",
        "version": "14.19.0-1"
    },
    "odoo": {
        "arch": "amd64",
        "digest": "86fd6e490d7fc7420bc96b8f56b53c734df8efe4333fc02633fbd51d8f1eb86f",
        "distro": "debian-10",
        "type": "NAMI",
        "version": "13.0.20220210-1"
    },
    "postgresql-client": {
        "arch": "amd64",
        "digest": "a7c2b602969129fb2de0267e6d3cee41d401fd5a85ebbdd95ba30dcff0b2e875",
        "distro": "debian-10",
        "type": "NAMI",
        "version": "13.6.0-0"
    },
    "python": {
        "arch": "amd64",
        "digest": "48db897c12810ff5f17a323e9b4a0cc2812e673d66f94feb9d90e3abb28e664b",
        "distro": "debian-10",
        "type": "NAMI",
        "version": "3.8.12-31"
    },
    "render-template": {
        "arch": "amd64",
        "digest": "ed811d10882450d4755b893d5e034a0dd912cdb4f261dd332ddf6363411cc0ba",
        "distro": "debian-10",
        "type": "NAMI",
        "version": "1.0.1-7"
    }
}