{
    "gosu": {
        "arch": "amd64",
        "digest": "7419bc5e2be68eb14c92e321acc843413481cda73323fb8c0d1dda8b1e5aa9d5",
        "distro": "debian-10",
        "type": "NAMI",
        "version": "1.14.0-2"
    },
    "java": {
        "arch": "amd64",
        "digest": "f7addf88d61b35543dc6ed9f5ec31fd8a800cec6249d419310fd56e8e9a3499d",
        "distro": "debian-10",
        "type": "NAMI",
        "version": "11.0.14-0"
    },
    "mysql-client": {
        "arch": "amd64",
        "digest": "727834a55587746f90b159966c9abf2ce31a6effbe83d8c38ee6250641c9a22a",
        "distro": "debian-10",
        "type": "NAMI",
        "version": "10.3.32-1"
    },
    "render-template": {
        "arch": "amd64",
        "digest": "9e312b4a7e16a55d08e67c4fd69c91000e4dcc4af149d59915c49375b83852af",
        "distro": "debian-10",
        "type": "NAMI",
        "version": "1.0.1-5"
    },
    "reportserverenterprise": {
        "arch": "amd64",
        "digest": "d8660b0421c6b17ad7ceedb30190f0a840b8cad5ad6d10c5d560b32d087495f4",
        "distro": "debian-10",
        "type": "NAMI",
        "version": "3.7.1-6052-1"
    },
    "tomcat": {
        "arch": "amd64",
        "digest": "94615d65980e65d4f4fe3dac073160e39a8a91af5f837f47160c523af6ce4e23",
        "distro": "debian-10",
        "type": "NAMI",
        "version": "9.0.58-0"
    }
}