{
    "gosu": {
        "arch": "amd64",
        "digest": "d6280b6f647a62bf6edc74dc8e526bfff63ddd8067dcb8540843f47203d9ccf1",
        "distro": "debian-10",
        "type": "NAMI",
        "version": "1.14.0-7"
    },
    "nginx": {
        "arch": "amd64",
        "digest": "cf552952f382072a5aecdc3d13876ce43aa634380b2fecdc039abf712762fa41",
        "distro": "debian-10",
        "type": "NAMI",
        "version": "1.20.2-37"
    },
    "render-template": {
        "arch": "amd64",
        "digest": "97c2ae4b001c5937e888b920bee7b1a40a076680caac53ded6d10f6207d54565",
        "distro": "debian-10",
        "type": "NAMI",
        "version": "1.0.1-10"
    }
}